{
  "id": "565035",
  "question": "Will the price of Bitcoin be less than $114K on July 25?",
  "conditionId": "0x7f1b31f81ebc01d946909eab08326762ee853fe48d03482ad316537b4b2638d8",
  "slug": "will-the-price-of-bitcoin-be-less-than-114k-on-july-25",
  "endDate": "2025-07-25T16:00:00Z",
  "startDate": "2025-07-18T14:49:30.093831Z",
  "image": "https://polymarket-upload.s3.us-east-2.amazonaws.com/BTC+fullsize.png",
  "icon": "https://polymarket-upload.s3.us-east-2.amazonaws.com/BTC+fullsize.png",
  "description": "This market will resolve according to the final \"Close\" price of the Binance 1 minute candle for BTC/USDT 12:00 in the ET timezone (noon) on the date specified in the title. Otherwise, this market will resolve to \"No\".\n\nThe resolution source for this market is Binance, specifically the BTC/USDT \"Close\" prices currently available at https://www.binance.com/en/trade/BTC_USDT with \"1m\" and \"Candles\" selected on the top bar..\n\nIf the reported value falls exactly between two brackets, then this market will resolve to the higher range bracket.\n\nPlease note that this market is about the price according to Binance BTC/USDT, not according to other sources or spot markets.",
  "outcomes": "[\"Yes\", \"No\"]",
  "outcomePrices": "[\"0\", \"1\"]",
  "volume": "428267.40588",
  "active": true,
  "closed": true,
  "marketMakerAddress": "",
  "createdAt": "2025-07-18T14:47:35.052159Z",
  "updatedAt": "2025-07-27T00:44:26.463455Z",
  "closedTime": "2025-07-25 19:07:47+00",
  "new": false,
  "featured": false,
  "submitted_by": "0x91430CaD2d3975766499717fA0D66A78D814E5c5",
  "archived": false,
  "resolvedBy": "0x2F5e3684cb1F318ec51b00Edba38d79Ac2c0aA9d",
  "restricted": true,
  "groupItemTitle": "<114k",
  "groupItemThreshold": "0",
  "questionID": "0x3b725df9219f4c602bd4a847df13e56de0bea702bcea8d5d083cb3cb2019a600",
  "umaEndDate": "2025-07-25T19:07:47Z",
  "enableOrderBook": true,
  "orderPriceMinTickSize": 0.001,
  "orderMinSize": 5,
  "umaResolutionStatus": "resolved",
  "volumeNum": 428267.40588,
  "endDateIso": "2025-07-25",
  "startDateIso": "2025-07-18",
  "hasReviewedDates": true,
  "volume1wk": 406760.8040910002,
  "volume1mo": 428267.4058800002,
  "volume1yr": 428267.4058800002,
  "clobTokenIds": "[\"26206602177704850453601056487912545409038167478968262921193381830033505959273\", \"82479753119294635275390000077165452043164711919562713911857288253230026838902\"]",
  "umaBond": "500",
  "umaReward": "5",
  "volume1wkClob": 406760.8040910002,
  "volume1moClob": 428267.4058800002,
  "volume1yrClob": 428267.4058800002,
  "volumeClob": 428267.40588,
  "customLiveness": 0,
  "acceptingOrders": false,
  "negRisk": true,
  "negRiskMarketID": "0x3b725df9219f4c602bd4a847df13e56de0bea702bcea8d5d083cb3cb2019a600",
  "negRiskRequestID": "0x449ac3c1b2a7be7dfaaacc8cdee1324ff9f9f50b4ae5f6d470bb2d6fac28f5ee",
  "events": [
    {
      "id": "33223",
      "ticker": "bitcoin-price-on-july-25",
      "slug": "bitcoin-price-on-july-25",
      "title": "Bitcoin price on July 25?",
      "description": "This market will resolve according to the final \"Close\" price of the Binance 1 minute candle for BTC/USDT 12:00 in the ET timezone (noon) on the date specified in the title. Otherwise, this market will resolve to \"No\".\n\nThe resolution source for this market is Binance, specifically the BTC/USDT \"Close\" prices currently available at https://www.binance.com/en/trade/BTC_USDT with \"1m\" and \"Candles\" selected on the top bar..\n\nIf the reported value falls exactly between two brackets, then this market will resolve to the higher range bracket.\n\nPlease note that this market is about the price according to Binance BTC/USDT, not according to other sources or spot markets.",
      "resolutionSource": "",
      "startDate": "2025-07-18T14:55:32.742052Z",
      "creationDate": "2025-07-18T14:55:32.742047Z",
      "endDate": "2025-07-25T16:00:00Z",
      "image": "https://polymarket-upload.s3.us-east-2.amazonaws.com/BTC+fullsize.png",
      "icon": "https://polymarket-upload.s3.us-east-2.amazonaws.com/BTC+fullsize.png",
      "active": true,
      "closed": true,
      "archived": false,
      "new": false,
      "featured": false,
      "restricted": true,
      "volume": 1935294.02245,
      "openInterest": 0,
      "createdAt": "2025-07-18T14:47:34.092537Z",
      "updatedAt": "2025-07-27T00:46:17.33679Z",
      "volume1wk": 1904104.6699180002,
      "volume1mo": 1935294.0224500003,
      "volume1yr": 1935294.0224500003,
      "enableOrderBook": true,
      "negRisk": true,
      "negRiskMarketID": "0x3b725df9219f4c602bd4a847df13e56de0bea702bcea8d5d083cb3cb2019a600",
      "commentCount": 1869,
      "series": [
        {
          "id": "10041",
          "ticker": "bitcoin-neg-risk-weekly",
          "slug": "bitcoin-neg-risk-weekly",
          "title": "Bitcoin Neg Risk Weekly",
          "seriesType": "single",
          "recurrence": "weekly",
          "image": "https://polymarket-upload.s3.us-east-2.amazonaws.com/bitcoin-price-on-february-14-DHM-RnCUzjpI.jpg",
          "icon": "https://polymarket-upload.s3.us-east-2.amazonaws.com/bitcoin-price-on-february-14-DHM-RnCUzjpI.jpg",
          "active": true,
          "closed": false,
          "archived": false,
          "featured": false,
          "restricted": true,
          "createdAt": "2025-02-07T17:51:26.959333Z",
          "updatedAt": "2026-01-14T12:15:05.595294Z",
          "volume": 1354190.631013,
          "liquidity": 1356495.27642,
          "commentCount": 1889,
          "requiresTranslation": false
        }
      ],
      "cyom": false,
      "closedTime": "2025-07-25T19:10:49Z",
      "showAllOutcomes": true,
      "showMarketImages": false,
      "automaticallyResolved": true,
      "enableNegRisk": true,
      "automaticallyActive": true,
      "seriesSlug": "btc-weekly-brackets",
      "gmpChartMode": "default",
      "negRiskAugmented": false,
      "pendingDeployment": false,
      "deploying": false,
      "deployingTimestamp": "2025-07-18T14:47:51.11384Z",
      "requiresTranslation": false
    }
  ],
  "ready": false,
  "funded": false,
  "acceptingOrdersTimestamp": "2025-07-18T14:49:06Z",
  "cyom": false,
  "pagerDutyNotificationEnabled": false,
  "approved": true,
  "rewardsMinSize": 0,
  "rewardsMaxSpread": 0,
  "spread": 0.001,
  "automaticallyResolved": true,
  "oneDayPriceChange": -0.0095,
  "oneWeekPriceChange": -0.2695,
  "lastTradePrice": 1,
  "bestAsk": 0.001,
  "automaticallyActive": true,
  "clearBookOnStart": true,
  "showGmpSeries": false,
  "showGmpOutcome": false,
  "manualActivation": false,
  "negRiskOther": false,
  "umaResolutionStatuses": "[\"proposed\", \"resolved\"]",
  "pendingDeployment": false,
  "deploying": false,
  "deployingTimestamp": "2025-07-18T14:48:17.032739Z",
  "rfqEnabled": false,
  "holdingRewardsEnabled": false,
  "feesEnabled": false,
  "requiresTranslation": false
}