{
  "id": "570585",
  "question": "Bitcoin Up or Down - August 3, 7AM ET",
  "conditionId": "0x52c77de7a71e9540d6b7fe3b4db87c5514f7d31bcd27e1916f833dd037ede76a",
  "slug": "bitcoin-up-or-down-august-3-7am-et",
  "resolutionSource": "https://www.binance.com/en/trade/BTC_USDT",
  "endDate": "2025-08-03T12:00:00Z",
  "startDate": "2025-08-01T10:49:06.317316Z",
  "image": "https://polymarket-upload.s3.us-east-2.amazonaws.com/BTC+fullsize.png",
  "icon": "https://polymarket-upload.s3.us-east-2.amazonaws.com/BTC+fullsize.png",
  "description": "This market will resolve to \"Up\" if the close price is greater than or equal to the open price for the BTC/USDT 1 Hour candle that begins on the time and date specified in the title. Otherwise, this market will resolve to \"Down\".\n\nThe resolution source for this market is information from Binance, specifically the BTC/USDT pair (https://www.binance.com/en/trade/BTC_USDT). The close \u00ab\u00a0C\u00a0\u00bb and open \u00ab\u00a0O\u00a0\u00bb displayed at the top of the graph for the relevant \"1H\" candle will be used once the data for that candle is finalized.\n\nPlease note that this market is about the price according to Binance BTC/USDT, not according to other sources or spot markets.",
  "outcomes": "[\"Up\", \"Down\"]",
  "outcomePrices": "[\"0\", \"1\"]",
  "volume": "88288.124922",
  "active": true,
  "closed": true,
  "marketMakerAddress": "0x8eEbcf33FdC6A0c93C657A822beB47a12E6a6F25",
  "createdAt": "2025-08-01T09:36:51.365521Z",
  "updatedAt": "2025-08-04T16:44:25.98952Z",
  "closedTime": "2025-08-03 13:00:33+00",
  "new": false,
  "featured": false,
  "submitted_by": "0x91430CaD2d3975766499717fA0D66A78D814E5c5",
  "archived": false,
  "resolvedBy": "0x157Ce2d672854c848c9b79C49a8Cc6cc89176a49",
  "restricted": true,
  "groupItemThreshold": "0",
  "questionID": "0x8350bece5bdf264ab883dfb9e805076962c2e8b9ab29ddfabfbcca37cb3aaf8b",
  "umaEndDate": "2025-08-03T13:00:33Z",
  "enableOrderBook": true,
  "orderPriceMinTickSize": 0.001,
  "orderMinSize": 5,
  "umaResolutionStatus": "resolved",
  "volumeNum": 88288.124922,
  "endDateIso": "2025-08-03",
  "startDateIso": "2025-08-01",
  "hasReviewedDates": true,
  "volume1wk": 88288.12492199994,
  "volume1mo": 88288.12492199994,
  "volume1yr": 88288.12492199994,
  "clobTokenIds": "[\"29826946104053466653492676668897569021352563122406925064002482297208943746912\", \"98997314355727856652715510115785932367489201683211265829215717052132402791508\"]",
  "umaBond": "500",
  "umaReward": "5",
  "volume1wkClob": 88288.12492199994,
  "volume1moClob": 88288.12492199994,
  "volume1yrClob": 88288.12492199994,
  "volumeClob": 88288.124922,
  "customLiveness": 3600,
  "acceptingOrders": false,
  "negRisk": false,
  "negRiskRequestID": "",
  "events": [
    {
      "id": "35220",
      "ticker": "bitcoin-up-or-down-august-3-7am-et",
      "slug": "bitcoin-up-or-down-august-3-7am-et",
      "title": "Bitcoin Up or Down - August 3, 7AM ET",
      "description": "This market will resolve to \"Up\" if the close price is greater than or equal to the open price for the BTC/USDT 1 Hour candle that begins on the time and date specified in the title. Otherwise, this market will resolve to \"Down\".\n\nThe resolution source for this market is information from Binance, specifically the BTC/USDT pair (https://www.binance.com/en/trade/BTC_USDT). The close \u00ab\u00a0C\u00a0\u00bb and open \u00ab\u00a0O\u00a0\u00bb displayed at the top of the graph for the relevant \"1H\" candle will be used once the data for that candle is finalized.\n\nPlease note that this market is about the price according to Binance BTC/USDT, not according to other sources or spot markets.",
      "resolutionSource": "https://www.binance.com/en/trade/BTC_USDT",
      "startDate": "2025-08-01T10:52:05.663217Z",
      "creationDate": "2025-08-01T10:52:05.663214Z",
      "endDate": "2025-08-03T12:00:00Z",
      "image": "https://polymarket-upload.s3.us-east-2.amazonaws.com/BTC+fullsize.png",
      "icon": "https://polymarket-upload.s3.us-east-2.amazonaws.com/BTC+fullsize.png",
      "active": true,
      "closed": true,
      "archived": false,
      "new": false,
      "featured": false,
      "restricted": true,
      "volume": 88288.124922,
      "openInterest": 0,
      "sortBy": "price",
      "createdAt": "2025-08-01T09:36:20.854171Z",
      "updatedAt": "2025-08-04T16:46:15.105377Z",
      "volume1wk": 88288.12492199994,
      "volume1mo": 88288.12492199994,
      "volume1yr": 88288.12492199994,
      "enableOrderBook": true,
      "negRisk": false,
      "commentCount": 6297,
      "series": [
        {
          "id": "10114",
          "ticker": "btc-up-or-down-hourly",
          "slug": "btc-up-or-down-hourly",
          "title": "BTC Up or Down Hourly",
          "seriesType": "single",
          "recurrence": "hourly",
          "image": "https://polymarket-upload.s3.us-east-2.amazonaws.com/BTC+fullsize.png",
          "icon": "https://polymarket-upload.s3.us-east-2.amazonaws.com/BTC+fullsize.png",
          "active": true,
          "closed": false,
          "archived": false,
          "featured": false,
          "restricted": true,
          "createdAt": "2025-05-27T12:19:33.928117Z",
          "updatedAt": "2026-01-14T12:11:12.733501Z",
          "volume": 714509.179452,
          "liquidity": 1351249.10563,
          "commentCount": 12208,
          "requiresTranslation": false
        }
      ],
      "cyom": false,
      "closedTime": "2025-08-03T13:00:33Z",
      "showAllOutcomes": true,
      "showMarketImages": true,
      "automaticallyResolved": true,
      "enableNegRisk": false,
      "automaticallyActive": true,
      "seriesSlug": "btc-up-or-down-hourly",
      "negRiskAugmented": false,
      "pendingDeployment": false,
      "deploying": false,
      "requiresTranslation": false
    }
  ],
  "ready": false,
  "funded": false,
  "acceptingOrdersTimestamp": "2025-08-01T10:48:46Z",
  "cyom": false,
  "pagerDutyNotificationEnabled": false,
  "approved": true,
  "rewardsMinSize": 0,
  "rewardsMaxSpread": 0,
  "spread": 0.001,
  "automaticallyResolved": true,
  "oneDayPriceChange": -0.495,
  "oneHourPriceChange": -0.495,
  "lastTradePrice": 1,
  "bestAsk": 0.001,
  "automaticallyActive": true,
  "clearBookOnStart": true,
  "showGmpSeries": false,
  "showGmpOutcome": false,
  "manualActivation": false,
  "negRiskOther": false,
  "umaResolutionStatuses": "[\"proposed\"]",
  "pendingDeployment": false,
  "deploying": false,
  "deployingTimestamp": "2025-08-01T10:25:44.42267Z",
  "rfqEnabled": false,
  "eventStartTime": "2025-08-03T11:00:00Z",
  "holdingRewardsEnabled": false,
  "feesEnabled": false,
  "requiresTranslation": false
}